{"match_index": 6843, "match_result": {"match_no": 6843, "result_dec": "West Indies won by 4 wickets (with 18 balls remaining)", "result": "WON", "winner": "West Indies", "special_case": ""}, "match_info": {"Match": "AUS vs WI, 2nd Final, Australia, Pakistan, West Indies in Australia, 1992-93", "Date": "Monday, January 18, 1993", "Toss": "Australia won the toss and opt to bat", "Time": "12:00 AM GMT", "Venue": "Melbourne Cricket Ground, Melbourne", "Umpires": "D Hair,\u00a0C Timmins", "Match Referee": "D Carr", "team_1": "AUS ", "team_2": " WI", "format": "limited-over"}, "squad": {"team_1": {"0": {"name": "Brian Lara", "link": "/profiles/240/brian-lara"}, "1": {"name": "Anderson Cummins", "link": "/profiles/683/anderson-cummins"}, "2": {"name": "Desmond Haynes", "link": "/profiles/4174/desmond-haynes"}, "3": {"name": "Gus Logie", "link": "/profiles/4186/gus-logie"}, "4": {"name": "Richie Richardson (c)", "link": "/profiles/4190/richie-richardson"}, "5": {"name": "Carl Hooper", "link": "/profiles/4199/carl-hooper"}, "6": {"name": "Phil Simmons", "link": "/profiles/4200/phil-simmons"}, "7": {"name": "Sir Curtly Ambrose", "link": "/profiles/4202/sir-curtly-ambrose"}, "8": {"name": "Ian Bishop", "link": "/profiles/4203/ian-bishop"}, "9": {"name": "Kenny Benjamin", "link": "/profiles/4209/kenny-benjamin"}, "10": {"name": "Junior Murray (wk)", "link": "/profiles/4210/junior-murray"}}, "team_2": {"0": {"name": "Brian Lara", "link": "/profiles/240/brian-lara"}, "1": {"name": "Anderson Cummins", "link": "/profiles/683/anderson-cummins"}, "2": {"name": "Desmond Haynes", "link": "/profiles/4174/desmond-haynes"}, "3": {"name": "Gus Logie", "link": "/profiles/4186/gus-logie"}, "4": {"name": "Richie Richardson (c)", "link": "/profiles/4190/richie-richardson"}, "5": {"name": "Carl Hooper", "link": "/profiles/4199/carl-hooper"}, "6": {"name": "Phil Simmons", "link": "/profiles/4200/phil-simmons"}, "7": {"name": "Sir Curtly Ambrose", "link": "/profiles/4202/sir-curtly-ambrose"}, "8": {"name": "Ian Bishop", "link": "/profiles/4203/ian-bishop"}, "9": {"name": "Kenny Benjamin", "link": "/profiles/4209/kenny-benjamin"}, "10": {"name": "Junior Murray (wk)", "link": "/profiles/4210/junior-murray"}}}, "match_scores": {"innings_1": {"batting_data": {"0": {"name": "David Boon", "result": "run out (Cummins)", "runs": "19", "balls": "50", "4": "1", "6": "0", "SR": "38.00", "link": "/profiles/4702/david-boon"}, "1": {"name": "Mark Taylor", "result": "c Ambrose b Bishop", "runs": "33", "balls": "73", "4": "2", "6": "0", "SR": "45.21", "link": "/profiles/4729/mark-taylor"}, "2": {"name": "Dean Jones", "result": "c Murray b Bishop", "runs": "5", "balls": "14", "4": "0", "6": "0", "SR": "35.71", "link": "/profiles/4701/dean-jones"}, "3": {"name": "Steve Waugh", "result": "run out (Hooper)", "runs": "25", "balls": "50", "4": "0", "6": "0", "SR": "50.00", "link": "/profiles/4712/steve-waugh"}, "4": {"name": "Mark Waugh", "result": "run out (Logie)", "runs": "8", "balls": "13", "4": "0", "6": "0", "SR": "61.54", "link": "/profiles/4727/mark-waugh"}, "5": {"name": "Allan Border (c)", "result": "c & b Hooper", "runs": "8", "balls": "13", "4": "0", "6": "0", "SR": "61.54", "link": "/profiles/4672/allan-border"}, "6": {"name": "Ian Healy (wk)", "result": "c & b Ambrose", "runs": "16", "balls": "26", "4": "0", "6": "0", "SR": "61.54", "link": "/profiles/4724/ian-healy"}, "7": {"name": "Greg Matthews", "result": "c Logie b Ambrose", "runs": "15", "balls": "25", "4": "0", "6": "0", "SR": "60.00", "link": "/profiles/4700/greg-matthews"}, "8": {"name": "Tony Dodemaide", "result": "c Murray b Ambrose", "runs": "1", "balls": "5", "4": "0", "6": "0", "SR": "20.00", "link": "/profiles/4723/tony-dodemaide"}, "9": {"name": "Paul Reiffel", "result": "not out", "runs": "7", "balls": "7", "4": "1", "6": "0", "SR": "100.00", "link": "/profiles/4730/paul-reiffel"}, "10": {"name": "Craig McDermott", "result": "b Hooper", "runs": "0", "balls": "3", "4": "0", "6": "0", "SR": "0.00", "link": "/profiles/4704/craig-mcdermott"}}, "bowling_data": {"0": {"name": "Ian Bishop", "overs": "9", "maiden": "2", "runs": "33", "wickets": "2", "no_balls": "3", "wides": "0", "economy": "3.67", "link": "/profiles/4203/ian-bishop"}, "1": {"name": "Kenny Benjamin", "overs": "10", "maiden": "0", "runs": "33", "wickets": "0", "no_balls": "4", "wides": "0", "economy": "3.30", "link": "/profiles/4209/kenny-benjamin"}, "2": {"name": "Sir Curtly Ambrose", "overs": "10", "maiden": "0", "runs": "26", "wickets": "3", "no_balls": "0", "wides": "0", "economy": "2.60", "link": "/profiles/4202/sir-curtly-ambrose"}, "3": {"name": "Anderson Cummins", "overs": "10", "maiden": "1", "runs": "24", "wickets": "0", "no_balls": "0", "wides": "0", "economy": "2.40", "link": "/profiles/683/anderson-cummins"}, "4": {"name": "Carl Hooper", "overs": "8.3", "maiden": "1", "runs": "28", "wickets": "2", "no_balls": "0", "wides": "0", "economy": "3.29", "link": "/profiles/4199/carl-hooper"}}}, "innings_2": {"batting_data": {"0": {"name": "Brian Lara", "result": "c ME Waugh b McDermott", "runs": "60", "balls": "100", "4": "5", "6": "0", "SR": "60.00", "link": "/profiles/240/brian-lara"}, "1": {"name": "Desmond Haynes", "result": "run out", "runs": "0", "balls": "3", "4": "0", "6": "0", "SR": "0.00", "link": "/profiles/4174/desmond-haynes"}, "2": {"name": "Phil Simmons", "result": "c ME Waugh b Dodemaide", "runs": "0", "balls": "1", "4": "0", "6": "0", "SR": "0.00", "link": "/profiles/4200/phil-simmons"}, "3": {"name": "Richie Richardson (c)", "result": "c Reiffel b McDermott", "runs": "5", "balls": "8", "4": "1", "6": "0", "SR": "62.50", "link": "/profiles/4190/richie-richardson"}, "4": {"name": "Carl Hooper", "result": "not out", "runs": "59", "balls": "132", "4": "3", "6": "0", "SR": "44.70", "link": "/profiles/4199/carl-hooper"}, "5": {"name": "Gus Logie", "result": "c Healy b Reiffel", "runs": "7", "balls": "7", "4": "0", "6": "0", "SR": "100.00", "link": "/profiles/4186/gus-logie"}, "6": {"name": "Junior Murray (wk)", "result": "c Healy b Dodemaide", "runs": "1", "balls": "12", "4": "0", "6": "0", "SR": "8.33", "link": "/profiles/4210/junior-murray"}, "7": {"name": "Ian Bishop", "result": "not out", "runs": "4", "balls": "25", "4": "0", "6": "0", "SR": "16.00", "link": "/profiles/4203/ian-bishop"}}, "bowling_data": {"0": {"name": "Craig McDermott", "overs": "10", "maiden": "0", "runs": "35", "wickets": "2", "no_balls": "1", "wides": "0", "economy": "3.50", "link": "/profiles/4704/craig-mcdermott"}, "1": {"name": "Tony Dodemaide", "overs": "10", "maiden": "4", "runs": "19", "wickets": "2", "no_balls": "0", "wides": "2", "economy": "1.90", "link": "/profiles/4723/tony-dodemaide"}, "2": {"name": "Steve Waugh", "overs": "10", "maiden": "1", "runs": "30", "wickets": "0", "no_balls": "0", "wides": "0", "economy": "3.00", "link": "/profiles/4712/steve-waugh"}, "3": {"name": "Mark Waugh", "overs": "4", "maiden": "0", "runs": "17", "wickets": "0", "no_balls": "1", "wides": "0", "economy": "4.25", "link": "/profiles/4727/mark-waugh"}, "4": {"name": "Paul Reiffel", "overs": "10", "maiden": "1", "runs": "21", "wickets": "1", "no_balls": "0", "wides": "0", "economy": "2.10", "link": "/profiles/4730/paul-reiffel"}, "5": {"name": "Greg Matthews", "overs": "3", "maiden": "0", "runs": "19", "wickets": "0", "no_balls": "0", "wides": "0", "economy": "6.33", "link": "/profiles/4700/greg-matthews"}}}}}