{"match_index": 6902, "match_result": {"match_no": 6902, "result_dec": "West Indies won by 69 runs (revised target)", "result": "WON", "winner": "West Indies", "special_case": ""}, "match_info": {"Match": "IND vs WI, 6th Match, India, South Africa, Sri Lanka, West Indies, Zimbabwe in India, 1993", "Date": "Tuesday, November 16, 1993", "Toss": "West Indies won the toss and opt to bat", "Time": "12:00 AM GMT", "Venue": "Sardar Patel Stadium, Ahmedabad", "Umpires": "K Liebenberg,\u00a0I Robinson", "team_1": "IND ", "team_2": " WI", "format": "limited-over"}, "squad": {"team_1": {"0": {"name": "Brian Lara", "link": "/profiles/240/brian-lara"}, "1": {"name": "Roger Harper", "link": "/profiles/4189/roger-harper"}, "2": {"name": "Richie Richardson (c)", "link": "/profiles/4190/richie-richardson"}, "3": {"name": "Courtney Walsh", "link": "/profiles/4194/courtney-walsh"}, "4": {"name": "Winston Benjamin", "link": "/profiles/4198/winston-benjamin"}, "5": {"name": "Carl Hooper", "link": "/profiles/4199/carl-hooper"}, "6": {"name": "Phil Simmons", "link": "/profiles/4200/phil-simmons"}, "7": {"name": "Sir Curtly Ambrose", "link": "/profiles/4202/sir-curtly-ambrose"}, "8": {"name": "Keith Arthurton", "link": "/profiles/4204/keith-arthurton"}, "9": {"name": "Jimmy Adams (wk)", "link": "/profiles/4211/jimmy-adams"}, "10": {"name": "Roland Holder", "link": "/profiles/4212/roland-holder"}}, "team_2": {"0": {"name": "Brian Lara", "link": "/profiles/240/brian-lara"}, "1": {"name": "Roger Harper", "link": "/profiles/4189/roger-harper"}, "2": {"name": "Richie Richardson (c)", "link": "/profiles/4190/richie-richardson"}, "3": {"name": "Courtney Walsh", "link": "/profiles/4194/courtney-walsh"}, "4": {"name": "Winston Benjamin", "link": "/profiles/4198/winston-benjamin"}, "5": {"name": "Carl Hooper", "link": "/profiles/4199/carl-hooper"}, "6": {"name": "Phil Simmons", "link": "/profiles/4200/phil-simmons"}, "7": {"name": "Sir Curtly Ambrose", "link": "/profiles/4202/sir-curtly-ambrose"}, "8": {"name": "Keith Arthurton", "link": "/profiles/4204/keith-arthurton"}, "9": {"name": "Jimmy Adams (wk)", "link": "/profiles/4211/jimmy-adams"}, "10": {"name": "Roland Holder", "link": "/profiles/4212/roland-holder"}}}, "match_scores": {"innings_1": {"batting_data": {"0": {"name": "Brian Lara", "result": "b Kumble", "runs": "23", "balls": "37", "4": "2", "6": "0", "SR": "62.16", "link": "/profiles/240/brian-lara"}, "1": {"name": "Phil Simmons", "result": "run out", "runs": "9", "balls": "36", "4": "1", "6": "0", "SR": "25.00", "link": "/profiles/4200/phil-simmons"}, "2": {"name": "Richie Richardson (c)", "result": "c Kambli b Kumble", "runs": "41", "balls": "69", "4": "6", "6": "1", "SR": "59.42", "link": "/profiles/4190/richie-richardson"}, "3": {"name": "Keith Arthurton", "result": "b Kumble", "runs": "41", "balls": "80", "4": "0", "6": "1", "SR": "51.25", "link": "/profiles/4204/keith-arthurton"}, "4": {"name": "Carl Hooper", "result": "c Yadav b Srinath", "runs": "8", "balls": "10", "4": "0", "6": "0", "SR": "80.00", "link": "/profiles/4199/carl-hooper"}, "5": {"name": "Jimmy Adams (wk)", "result": "not out", "runs": "26", "balls": "33", "4": "0", "6": "0", "SR": "78.79", "link": "/profiles/4211/jimmy-adams"}, "6": {"name": "Roland Holder", "result": "c Chauhan b Srinath", "runs": "10", "balls": "16", "4": "0", "6": "0", "SR": "62.50", "link": "/profiles/4212/roland-holder"}, "7": {"name": "Roger Harper", "result": "run out", "runs": "2", "balls": "5", "4": "0", "6": "0", "SR": "40.00", "link": "/profiles/4189/roger-harper"}, "8": {"name": "Winston Benjamin", "result": "not out", "runs": "14", "balls": "14", "4": "1", "6": "0", "SR": "100.00", "link": "/profiles/4198/winston-benjamin"}}, "bowling_data": {"0": {"name": "Manoj Prabhakar", "overs": "10", "maiden": "1", "runs": "50", "wickets": "0", "no_balls": "0", "wides": "0", "economy": "5.00", "link": "/profiles/3860/manoj-prabhakar"}, "1": {"name": "Javagal Srinath", "overs": "10", "maiden": "1", "runs": "33", "wickets": "2", "no_balls": "0", "wides": "0", "economy": "3.30", "link": "/profiles/3894/javagal-srinath"}, "2": {"name": "Anil Kumble", "overs": "10", "maiden": "1", "runs": "24", "wickets": "3", "no_balls": "0", "wides": "0", "economy": "2.40", "link": "/profiles/98/anil-kumble"}, "3": {"name": "Kapil Dev", "overs": "8", "maiden": "0", "runs": "21", "wickets": "0", "no_balls": "0", "wides": "0", "economy": "2.63", "link": "/profiles/3838/kapil-dev"}, "4": {"name": "Rajesh Chauhan", "overs": "10", "maiden": "2", "runs": "41", "wickets": "0", "no_balls": "0", "wides": "0", "economy": "4.10", "link": "/profiles/3900/rajesh-chauhan"}, "5": {"name": "Sachin Tendulkar", "overs": "2", "maiden": "0", "runs": "11", "wickets": "0", "no_balls": "0", "wides": "0", "economy": "5.50", "link": "/profiles/25/sachin-tendulkar"}}}, "innings_2": {"batting_data": {"0": {"name": "Manoj Prabhakar", "result": "c Adams b Walsh", "runs": "11", "balls": "14", "4": "2", "6": "0", "SR": "78.57", "link": "/profiles/3860/manoj-prabhakar"}, "1": {"name": "Kapil Dev", "result": "lbw b Ambrose", "runs": "1", "balls": "2", "4": "0", "6": "0", "SR": "50.00", "link": "/profiles/3838/kapil-dev"}, "2": {"name": "Vinod Kambli", "result": "c Lara b Benjamin", "runs": "10", "balls": "18", "4": "1", "6": "0", "SR": "55.56", "link": "/profiles/3893/vinod-kambli"}, "3": {"name": "Mohammad Azharuddin (c)", "result": "c Ambrose b Simmons", "runs": "23", "balls": "44", "4": "2", "6": "0", "SR": "52.27", "link": "/profiles/3864/mohammad-azharuddin"}, "4": {"name": "Sachin Tendulkar", "result": "lbw b Walsh", "runs": "2", "balls": "8", "4": "0", "6": "0", "SR": "25.00", "link": "/profiles/25/sachin-tendulkar"}, "5": {"name": "Woorkeri Raman", "result": "c Lara b Benjamin", "runs": "4", "balls": "14", "4": "0", "6": "0", "SR": "28.57", "link": "/profiles/3876/woorkeri-raman"}, "6": {"name": "Ajay Sharma", "result": "b Benjamin", "runs": "0", "balls": "1", "4": "0", "6": "0", "SR": "0.00", "link": "/profiles/3877/ajay-sharma"}, "7": {"name": "Vijay Yadav (wk)", "result": "st Adams b Hooper", "runs": "20", "balls": "26", "4": "2", "6": "0", "SR": "76.92", "link": "/profiles/3899/vijay-yadav"}, "8": {"name": "Anil Kumble", "result": "c Benjamin b Hooper", "runs": "14", "balls": "27", "4": "1", "6": "0", "SR": "51.85", "link": "/profiles/98/anil-kumble"}, "9": {"name": "Rajesh Chauhan", "result": "not out", "runs": "3", "balls": "10", "4": "0", "6": "0", "SR": "30.00", "link": "/profiles/3900/rajesh-chauhan"}, "10": {"name": "Javagal Srinath", "result": "c Harper b Hooper", "runs": "2", "balls": "8", "4": "0", "6": "0", "SR": "25.00", "link": "/profiles/3894/javagal-srinath"}}, "bowling_data": {"0": {"name": "Sir Curtly Ambrose", "overs": "6", "maiden": "0", "runs": "18", "wickets": "1", "no_balls": "0", "wides": "5", "economy": "3.00", "link": "/profiles/4202/sir-curtly-ambrose"}, "1": {"name": "Courtney Walsh", "overs": "7", "maiden": "2", "runs": "25", "wickets": "2", "no_balls": "0", "wides": "2", "economy": "3.57", "link": "/profiles/4194/courtney-walsh"}, "2": {"name": "Phil Simmons", "overs": "5", "maiden": "0", "runs": "19", "wickets": "1", "no_balls": "0", "wides": "1", "economy": "3.80", "link": "/profiles/4200/phil-simmons"}, "3": {"name": "Winston Benjamin", "overs": "6", "maiden": "0", "runs": "27", "wickets": "3", "no_balls": "0", "wides": "0", "economy": "4.50", "link": "/profiles/4198/winston-benjamin"}, "4": {"name": "Carl Hooper", "overs": "4.3", "maiden": "1", "runs": "9", "wickets": "3", "no_balls": "0", "wides": "0", "economy": "2.00", "link": "/profiles/4199/carl-hooper"}}}}}