{"match_index": 4018, "match_result": {"match_no": 4018, "result_dec": "Kenya won by 6 runs", "result": "WON", "winner": "Kenya", "special_case": ""}, "match_info": {"Match": "KEN vs SCO, 4th Match, Canada, Kenya, Scotland in Kenya", "Date": "Sunday, January 21, 2007", "Toss": "Kenya won the toss and opt to bat", "Time": "07:00 AM GMT", "Venue": "Mombasa Sports Club Ground, Mombasa", "Umpires": "I Gould,\u00a0D Hair", "Match Referee": "J Srinath", "team_1": "KEN ", "team_2": " SCO", "format": "limited-over"}, "squad": {"team_1": {"0": {"name": "John Blain", "link": "/profiles/643/john-blain"}, "1": {"name": "Dougie Brown", "link": "/profiles/644/dougie-brown"}, "2": {"name": "Gavin Hamilton (wk)", "link": "/profiles/645/gavin-hamilton"}, "3": {"name": "Majid Haq", "link": "/profiles/646/majid-haq"}, "4": {"name": "Ross Lyons", "link": "/profiles/650/ross-lyons"}, "5": {"name": "Neil McCallum", "link": "/profiles/651/neil-mccallum"}, "6": {"name": "Dewald Nel", "link": "/profiles/652/dewald-nel"}, "7": {"name": "Navdeep Poonia", "link": "/profiles/653/navdeep-poonia"}, "8": {"name": "Ryan Watson (c)", "link": "/profiles/655/ryan-watson"}, "9": {"name": "Fraser Watts", "link": "/profiles/656/fraser-watts"}, "10": {"name": "Glenn Rogers", "link": "/profiles/693/glenn-rogers"}}, "team_2": {"0": {"name": "John Blain", "link": "/profiles/643/john-blain"}, "1": {"name": "Dougie Brown", "link": "/profiles/644/dougie-brown"}, "2": {"name": "Gavin Hamilton (wk)", "link": "/profiles/645/gavin-hamilton"}, "3": {"name": "Majid Haq", "link": "/profiles/646/majid-haq"}, "4": {"name": "Ross Lyons", "link": "/profiles/650/ross-lyons"}, "5": {"name": "Neil McCallum", "link": "/profiles/651/neil-mccallum"}, "6": {"name": "Dewald Nel", "link": "/profiles/652/dewald-nel"}, "7": {"name": "Navdeep Poonia", "link": "/profiles/653/navdeep-poonia"}, "8": {"name": "Ryan Watson (c)", "link": "/profiles/655/ryan-watson"}, "9": {"name": "Fraser Watts", "link": "/profiles/656/fraser-watts"}, "10": {"name": "Glenn Rogers", "link": "/profiles/693/glenn-rogers"}}}, "match_scores": {"innings_1": {"batting_data": {"0": {"name": "Morris Ouma (wk)", "result": "run out (Rogers)", "runs": "14", "balls": "27", "4": "1", "6": "0", "SR": "51.85", "link": "/profiles/194/morris-ouma"}, "1": {"name": "David Obuya", "result": "lbw b Brown", "runs": "36", "balls": "42", "4": "7", "6": "0", "SR": "85.71", "link": "/profiles/658/david-obuya"}, "2": {"name": "Ravi Shah", "result": "st Hamilton b Lyons", "runs": "113", "balls": "121", "4": "8", "6": "3", "SR": "93.39", "link": "/profiles/197/ravi-shah"}, "3": {"name": "Steve Tikolo (c)", "result": "lbw b Nel", "runs": "0", "balls": "4", "4": "0", "6": "0", "SR": "0.00", "link": "/profiles/186/steve-tikolo"}, "4": {"name": "Tanmay Mishra", "result": "lbw b Brown", "runs": "0", "balls": "4", "4": "0", "6": "0", "SR": "0.00", "link": "/profiles/551/tanmay-mishra"}, "5": {"name": "Collins Obuya", "result": "c Nel b Brown", "runs": "5", "balls": "12", "4": "1", "6": "0", "SR": "41.67", "link": "/profiles/550/collins-obuya"}, "6": {"name": "Thomas Odoyo", "result": "c Watts b Lyons", "runs": "39", "balls": "64", "4": "3", "6": "1", "SR": "60.94", "link": "/profiles/190/thomas-odoyo"}, "7": {"name": "Jimmy Kamande", "result": "run out (Watson)", "runs": "10", "balls": "10", "4": "1", "6": "0", "SR": "100.00", "link": "/profiles/549/jimmy-kamande"}, "8": {"name": "Nehemiah Odhiambo", "result": "lbw b Haq", "runs": "2", "balls": "4", "4": "0", "6": "0", "SR": "50.00", "link": "/profiles/552/nehemiah-odhiambo"}, "9": {"name": "Peter Ongondo", "result": "not out", "runs": "11", "balls": "12", "4": "0", "6": "0", "SR": "91.67", "link": "/profiles/191/peter-ongondo"}, "10": {"name": "Hiren Varaiya", "result": "not out", "runs": "2", "balls": "2", "4": "0", "6": "0", "SR": "100.00", "link": "/profiles/553/hiren-varaiya"}}, "bowling_data": {"0": {"name": "John Blain", "overs": "8", "maiden": "0", "runs": "37", "wickets": "0", "no_balls": "2", "wides": "4", "economy": "4.63", "link": "/profiles/643/john-blain"}, "1": {"name": "Dougie Brown", "overs": "10", "maiden": "1", "runs": "37", "wickets": "3", "no_balls": "0", "wides": "3", "economy": "3.70", "link": "/profiles/644/dougie-brown"}, "2": {"name": "Dewald Nel", "overs": "8", "maiden": "0", "runs": "42", "wickets": "1", "no_balls": "0", "wides": "0", "economy": "5.25", "link": "/profiles/652/dewald-nel"}, "3": {"name": "Majid Haq", "overs": "10", "maiden": "0", "runs": "45", "wickets": "1", "no_balls": "0", "wides": "2", "economy": "4.50", "link": "/profiles/646/majid-haq"}, "4": {"name": "Glenn Rogers", "overs": "9", "maiden": "0", "runs": "55", "wickets": "0", "no_balls": "0", "wides": "0", "economy": "6.11", "link": "/profiles/693/glenn-rogers"}, "5": {"name": "Ross Lyons", "overs": "5", "maiden": "0", "runs": "28", "wickets": "2", "no_balls": "0", "wides": "0", "economy": "5.60", "link": "/profiles/650/ross-lyons"}}}, "innings_2": {"batting_data": {"0": {"name": "Fraser Watts", "result": "c & b Varaiya", "runs": "59", "balls": "102", "4": "5", "6": "2", "SR": "57.84", "link": "/profiles/656/fraser-watts"}, "1": {"name": "Majid Haq", "result": "b Kamande", "runs": "59", "balls": "88", "4": "10", "6": "0", "SR": "67.05", "link": "/profiles/646/majid-haq"}, "2": {"name": "Ryan Watson (c)", "result": "c Ouma b Kamande", "runs": "31", "balls": "33", "4": "3", "6": "0", "SR": "93.94", "link": "/profiles/655/ryan-watson"}, "3": {"name": "Gavin Hamilton (wk)", "result": "not out", "runs": "46", "balls": "38", "4": "4", "6": "1", "SR": "121.05", "link": "/profiles/645/gavin-hamilton"}, "4": {"name": "Neil McCallum", "result": "c DO Obuya b Tikolo", "runs": "27", "balls": "26", "4": "3", "6": "1", "SR": "103.85", "link": "/profiles/651/neil-mccallum"}, "5": {"name": "Dougie Brown", "result": "c Mishra b Tikolo", "runs": "0", "balls": "2", "4": "0", "6": "0", "SR": "0.00", "link": "/profiles/644/dougie-brown"}, "6": {"name": "Navdeep Poonia", "result": "c Kamande b Tikolo", "runs": "0", "balls": "2", "4": "0", "6": "0", "SR": "0.00", "link": "/profiles/653/navdeep-poonia"}, "7": {"name": "John Blain", "result": "run out (Kamande)", "runs": "2", "balls": "3", "4": "0", "6": "0", "SR": "66.67", "link": "/profiles/643/john-blain"}, "8": {"name": "Glenn Rogers", "result": "st Ouma b Tikolo", "runs": "1", "balls": "3", "4": "0", "6": "0", "SR": "33.33", "link": "/profiles/693/glenn-rogers"}, "9": {"name": "Ross Lyons", "result": "not out", "runs": "6", "balls": "8", "4": "0", "6": "0", "SR": "75.00", "link": "/profiles/650/ross-lyons"}}, "bowling_data": {"0": {"name": "Thomas Odoyo", "overs": "10", "maiden": "0", "runs": "56", "wickets": "0", "no_balls": "0", "wides": "1", "economy": "5.60", "link": "/profiles/190/thomas-odoyo"}, "1": {"name": "Peter Ongondo", "overs": "7", "maiden": "0", "runs": "22", "wickets": "0", "no_balls": "1", "wides": "0", "economy": "3.14", "link": "/profiles/191/peter-ongondo"}, "2": {"name": "Nehemiah Odhiambo", "overs": "5", "maiden": "0", "runs": "37", "wickets": "0", "no_balls": "4", "wides": "1", "economy": "7.40", "link": "/profiles/552/nehemiah-odhiambo"}, "3": {"name": "Steve Tikolo (c)", "overs": "10", "maiden": "1", "runs": "41", "wickets": "4", "no_balls": "0", "wides": "3", "economy": "4.10", "link": "/profiles/186/steve-tikolo"}, "4": {"name": "Hiren Varaiya", "overs": "10", "maiden": "0", "runs": "40", "wickets": "1", "no_balls": "0", "wides": "0", "economy": "4.00", "link": "/profiles/553/hiren-varaiya"}, "5": {"name": "Jimmy Kamande", "overs": "8", "maiden": "0", "runs": "50", "wickets": "2", "no_balls": "0", "wides": "1", "economy": "6.25", "link": "/profiles/549/jimmy-kamande"}}}}}