{"match_index": 4144, "match_result": {"match_no": 4144, "result_dec": "Australia won by 277 runs", "result": "WON", "winner": "Australia", "special_case": ""}, "match_info": {"Match": "AUS vs ENG, 1st Test, England in Australia, 2006-07", "Date": "Thursday, November 23, 2006 - Monday, November 27, 2006", "Toss": "Australia won the toss and opt to bat", "Time": "12:00 AM GMT", "Venue": "The Gabba, Brisbane", "Umpires": "Billy Bowden,\u00a0S Bucknor", "Third Umpire": "P Parker", "Match Referee": "J Crowe", "team_1": "AUS ", "team_2": " ENG", "format": "Test"}, "squad": {"team_1": {"0": {"name": "Andrew Flintoff (c)", "link": "/profiles/61/andrew-flintoff"}, "1": {"name": "Steve Harmison", "link": "/profiles/62/steve-harmison"}, "2": {"name": "James Anderson", "link": "/profiles/65/james-anderson"}, "3": {"name": "Paul Collingwood", "link": "/profiles/66/paul-collingwood"}, "4": {"name": "Ashley Giles", "link": "/profiles/164/ashley-giles"}, "5": {"name": "Geraint Jones (wk)", "link": "/profiles/165/geraint-jones"}, "6": {"name": "Sir Andrew Strauss", "link": "/profiles/167/sir-andrew-strauss"}, "7": {"name": "Ian Bell", "link": "/profiles/385/ian-bell"}, "8": {"name": "Matthew Hoggard", "link": "/profiles/386/matthew-hoggard"}, "9": {"name": "Kevin Pietersen", "link": "/profiles/395/kevin-pietersen"}, "10": {"name": "Sir Alastair Cook", "link": "/profiles/488/sir-alastair-cook"}}, "team_2": {"0": {"name": "Andrew Flintoff (c)", "link": "/profiles/61/andrew-flintoff"}, "1": {"name": "Steve Harmison", "link": "/profiles/62/steve-harmison"}, "2": {"name": "James Anderson", "link": "/profiles/65/james-anderson"}, "3": {"name": "Paul Collingwood", "link": "/profiles/66/paul-collingwood"}, "4": {"name": "Ashley Giles", "link": "/profiles/164/ashley-giles"}, "5": {"name": "Geraint Jones (wk)", "link": "/profiles/165/geraint-jones"}, "6": {"name": "Sir Andrew Strauss", "link": "/profiles/167/sir-andrew-strauss"}, "7": {"name": "Ian Bell", "link": "/profiles/385/ian-bell"}, "8": {"name": "Matthew Hoggard", "link": "/profiles/386/matthew-hoggard"}, "9": {"name": "Kevin Pietersen", "link": "/profiles/395/kevin-pietersen"}, "10": {"name": "Sir Alastair Cook", "link": "/profiles/488/sir-alastair-cook"}}}, "match_scores": {"innings_1": {"batting_data": {"0": {"name": "Justin Langer", "result": "c Pietersen b Flintoff", "runs": "82", "balls": "98", "4": "13", "6": "0", "SR": "83.67", "link": "/profiles/281/justin-langer"}, "1": {"name": "Matthew Hayden", "result": "c Collingwood b Flintoff", "runs": "21", "balls": "47", "4": "2", "6": "0", "SR": "44.68", "link": "/profiles/157/matthew-hayden"}, "2": {"name": "Ricky Ponting (c)", "result": "lbw b Hoggard", "runs": "196", "balls": "319", "4": "24", "6": "0", "SR": "61.44", "link": "/profiles/38/ricky-ponting"}, "3": {"name": "Damien Martyn", "result": "c Collingwood b Giles", "runs": "29", "balls": "62", "4": "2", "6": "0", "SR": "46.77", "link": "/profiles/136/damien-martyn"}, "4": {"name": "Michael Hussey", "result": "b Flintoff", "runs": "86", "balls": "187", "4": "8", "6": "0", "SR": "45.99", "link": "/profiles/4772/michael-hussey"}, "5": {"name": "Michael Clarke", "result": "c Strauss b Anderson", "runs": "56", "balls": "94", "4": "5", "6": "1", "SR": "59.57", "link": "/profiles/138/michael-clarke"}, "6": {"name": "Adam Gilchrist (wk)", "result": "lbw b Hoggard", "runs": "0", "balls": "3", "4": "0", "6": "0", "SR": "0.00", "link": "/profiles/36/adam-gilchrist"}, "7": {"name": "Shane Warne", "result": "c Jones b Harmison", "runs": "17", "balls": "26", "4": "1", "6": "0", "SR": "65.38", "link": "/profiles/135/shane-warne"}, "8": {"name": "Brett Lee", "result": "not out", "runs": "43", "balls": "61", "4": "6", "6": "0", "SR": "70.49", "link": "/profiles/42/brett-lee"}, "9": {"name": "Stuart Clark", "result": "b Flintoff", "runs": "39", "balls": "23", "4": "3", "6": "2", "SR": "169.57", "link": "/profiles/432/stuart-clark"}, "10": {"name": "Glenn McGrath", "result": "not out", "runs": "8", "balls": "17", "4": "0", "6": "0", "SR": "47.06", "link": "/profiles/41/glenn-mcgrath"}}, "bowling_data": {"0": {"name": "Steve Harmison", "overs": "30", "maiden": "4", "runs": "123", "wickets": "1", "no_balls": "1", "wides": "6", "economy": "4.10", "link": "/profiles/62/steve-harmison"}, "1": {"name": "Matthew Hoggard", "overs": "31", "maiden": "5", "runs": "98", "wickets": "2", "no_balls": "1", "wides": "0", "economy": "3.16", "link": "/profiles/386/matthew-hoggard"}, "2": {"name": "James Anderson", "overs": "29", "maiden": "6", "runs": "141", "wickets": "1", "no_balls": "0", "wides": "1", "economy": "4.86", "link": "/profiles/65/james-anderson"}, "3": {"name": "Andrew Flintoff (c)", "overs": "30", "maiden": "4", "runs": "99", "wickets": "4", "no_balls": "3", "wides": "1", "economy": "3.30", "link": "/profiles/61/andrew-flintoff"}, "4": {"name": "Ashley Giles", "overs": "25", "maiden": "2", "runs": "91", "wickets": "1", "no_balls": "0", "wides": "0", "economy": "3.64", "link": "/profiles/164/ashley-giles"}, "5": {"name": "Ian Bell", "overs": "1", "maiden": "0", "runs": "12", "wickets": "0", "no_balls": "2", "wides": "0", "economy": "12.00", "link": "/profiles/385/ian-bell"}, "6": {"name": "Kevin Pietersen", "overs": "9", "maiden": "1", "runs": "28", "wickets": "0", "no_balls": "0", "wides": "0", "economy": "3.11", "link": "/profiles/395/kevin-pietersen"}}}, "innings_2": {"batting_data": {"0": {"name": "Sir Andrew Strauss", "result": "c Hussey b McGrath", "runs": "12", "balls": "21", "4": "2", "6": "0", "SR": "57.14", "link": "/profiles/167/sir-andrew-strauss"}, "1": {"name": "Sir Alastair Cook", "result": "c Warne b McGrath", "runs": "11", "balls": "15", "4": "1", "6": "0", "SR": "73.33", "link": "/profiles/488/sir-alastair-cook"}, "2": {"name": "Ian Bell", "result": "c Ponting b Clark", "runs": "50", "balls": "162", "4": "5", "6": "0", "SR": "30.86", "link": "/profiles/385/ian-bell"}, "3": {"name": "Paul Collingwood", "result": "c Gilchrist b Clark", "runs": "5", "balls": "13", "4": "1", "6": "0", "SR": "38.46", "link": "/profiles/66/paul-collingwood"}, "4": {"name": "Kevin Pietersen", "result": "lbw b McGrath", "runs": "16", "balls": "44", "4": "1", "6": "0", "SR": "36.36", "link": "/profiles/395/kevin-pietersen"}, "5": {"name": "Andrew Flintoff (c)", "result": "c Gilchrist b Lee", "runs": "0", "balls": "3", "4": "0", "6": "0", "SR": "0.00", "link": "/profiles/61/andrew-flintoff"}, "6": {"name": "Geraint Jones (wk)", "result": "lbw b McGrath", "runs": "19", "balls": "57", "4": "2", "6": "0", "SR": "33.33", "link": "/profiles/165/geraint-jones"}, "7": {"name": "Ashley Giles", "result": "c Hayden b McGrath", "runs": "24", "balls": "39", "4": "4", "6": "0", "SR": "61.54", "link": "/profiles/164/ashley-giles"}, "8": {"name": "Matthew Hoggard", "result": "c Gilchrist b Clark", "runs": "0", "balls": "6", "4": "0", "6": "0", "SR": "0.00", "link": "/profiles/386/matthew-hoggard"}, "9": {"name": "Steve Harmison", "result": "c Gilchrist b McGrath", "runs": "0", "balls": "5", "4": "0", "6": "0", "SR": "0.00", "link": "/profiles/62/steve-harmison"}, "10": {"name": "James Anderson", "result": "not out", "runs": "2", "balls": "8", "4": "0", "6": "0", "SR": "25.00", "link": "/profiles/65/james-anderson"}}, "bowling_data": {"0": {"name": "Brett Lee", "overs": "15", "maiden": "3", "runs": "51", "wickets": "1", "no_balls": "5", "wides": "2", "economy": "3.40", "link": "/profiles/42/brett-lee"}, "1": {"name": "Glenn McGrath", "overs": "23.1", "maiden": "8", "runs": "50", "wickets": "6", "no_balls": "1", "wides": "0", "economy": "2.16", "link": "/profiles/41/glenn-mcgrath"}, "2": {"name": "Stuart Clark", "overs": "14", "maiden": "5", "runs": "21", "wickets": "3", "no_balls": "0", "wides": "0", "economy": "1.50", "link": "/profiles/432/stuart-clark"}, "3": {"name": "Shane Warne", "overs": "9", "maiden": "0", "runs": "25", "wickets": "0", "no_balls": "0", "wides": "0", "economy": "2.78", "link": "/profiles/135/shane-warne"}}}, "innings_3": {"batting_data": {"0": {"name": "Justin Langer", "result": "not out", "runs": "100", "balls": "146", "4": "9", "6": "0", "SR": "68.49", "link": "/profiles/281/justin-langer"}, "1": {"name": "Matthew Hayden", "result": "run out (Anderson/Jones)", "runs": "37", "balls": "41", "4": "6", "6": "0", "SR": "90.24", "link": "/profiles/157/matthew-hayden"}, "2": {"name": "Ricky Ponting (c)", "result": "not out", "runs": "60", "balls": "85", "4": "4", "6": "0", "SR": "70.59", "link": "/profiles/38/ricky-ponting"}}, "bowling_data": {"0": {"name": "Matthew Hoggard", "overs": "11", "maiden": "2", "runs": "43", "wickets": "0", "no_balls": "0", "wides": "0", "economy": "3.91", "link": "/profiles/386/matthew-hoggard"}, "1": {"name": "James Anderson", "overs": "9", "maiden": "1", "runs": "54", "wickets": "0", "no_balls": "0", "wides": "0", "economy": "6.00", "link": "/profiles/65/james-anderson"}, "2": {"name": "Andrew Flintoff (c)", "overs": "5", "maiden": "2", "runs": "11", "wickets": "0", "no_balls": "1", "wides": "0", "economy": "2.20", "link": "/profiles/61/andrew-flintoff"}, "3": {"name": "Steve Harmison", "overs": "12.1", "maiden": "1", "runs": "54", "wickets": "0", "no_balls": "0", "wides": "0", "economy": "4.44", "link": "/profiles/62/steve-harmison"}, "4": {"name": "Ashley Giles", "overs": "5", "maiden": "0", "runs": "22", "wickets": "0", "no_balls": "0", "wides": "0", "economy": "4.40", "link": "/profiles/164/ashley-giles"}, "5": {"name": "Kevin Pietersen", "overs": "3", "maiden": "0", "runs": "14", "wickets": "0", "no_balls": "0", "wides": "0", "economy": "4.67", "link": "/profiles/395/kevin-pietersen"}}}, "innings_4": {"batting_data": {"0": {"name": "Sir Andrew Strauss", "result": "c sub (RA Broad) b Clark", "runs": "11", "balls": "31", "4": "1", "6": "0", "SR": "35.48", "link": "/profiles/167/sir-andrew-strauss"}, "1": {"name": "Sir Alastair Cook", "result": "c Hussey b Warne", "runs": "43", "balls": "94", "4": "4", "6": "0", "SR": "45.74", "link": "/profiles/488/sir-alastair-cook"}, "2": {"name": "Ian Bell", "result": "lbw b Warne", "runs": "0", "balls": "4", "4": "0", "6": "0", "SR": "0.00", "link": "/profiles/385/ian-bell"}, "3": {"name": "Paul Collingwood", "result": "st Gilchrist b Warne", "runs": "96", "balls": "155", "4": "13", "6": "2", "SR": "61.94", "link": "/profiles/66/paul-collingwood"}, "4": {"name": "Kevin Pietersen", "result": "c Martyn b Lee", "runs": "92", "balls": "155", "4": "14", "6": "0", "SR": "59.35", "link": "/profiles/395/kevin-pietersen"}, "5": {"name": "Andrew Flintoff (c)", "result": "c Langer b Warne", "runs": "16", "balls": "26", "4": "4", "6": "0", "SR": "61.54", "link": "/profiles/61/andrew-flintoff"}, "6": {"name": "Geraint Jones (wk)", "result": "b McGrath", "runs": "33", "balls": "48", "4": "5", "6": "0", "SR": "68.75", "link": "/profiles/165/geraint-jones"}, "7": {"name": "Ashley Giles", "result": "c Warne b Clark", "runs": "23", "balls": "38", "4": "3", "6": "0", "SR": "60.53", "link": "/profiles/164/ashley-giles"}, "8": {"name": "Matthew Hoggard", "result": "c Warne b Clark", "runs": "8", "balls": "35", "4": "1", "6": "0", "SR": "22.86", "link": "/profiles/386/matthew-hoggard"}, "9": {"name": "Steve Harmison", "result": "c McGrath b Clark", "runs": "13", "balls": "18", "4": "2", "6": "0", "SR": "72.22", "link": "/profiles/62/steve-harmison"}, "10": {"name": "James Anderson", "result": "not out", "runs": "4", "balls": "8", "4": "1", "6": "0", "SR": "50.00", "link": "/profiles/65/james-anderson"}}, "bowling_data": {"0": {"name": "Brett Lee", "overs": "22", "maiden": "1", "runs": "98", "wickets": "1", "no_balls": "7", "wides": "1", "economy": "4.45", "link": "/profiles/42/brett-lee"}, "1": {"name": "Glenn McGrath", "overs": "19", "maiden": "3", "runs": "53", "wickets": "1", "no_balls": "3", "wides": "0", "economy": "2.79", "link": "/profiles/41/glenn-mcgrath"}, "2": {"name": "Stuart Clark", "overs": "24.1", "maiden": "6", "runs": "72", "wickets": "4", "no_balls": "0", "wides": "0", "economy": "2.98", "link": "/profiles/432/stuart-clark"}, "3": {"name": "Shane Warne", "overs": "34", "maiden": "7", "runs": "124", "wickets": "4", "no_balls": "1", "wides": "1", "economy": "3.65", "link": "/profiles/135/shane-warne"}, "4": {"name": "Michael Hussey", "overs": "1", "maiden": "0", "runs": "5", "wickets": "0", "no_balls": "0", "wides": "0", "economy": "5.00", "link": "/profiles/4772/michael-hussey"}}}}}