{"match_index": 5781, "match_result": {"match_no": 5781, "result_dec": "No result", "result": "NA", "winner": "NA", "special_case": ""}, "match_info": {"Match": "ENG vs WI, 3rd Match, England, West Indies, Zimbabwe in England, 2000", "Date": "Sunday, July 09, 2000", "Toss": "West Indies won the toss and opt to bowl", "Time": "12:00 AM GMT", "Venue": "Lord's, London", "Umpires": "R Julian,\u00a0K Palmer", "Third Umpire": "B Dudleston", "Match Referee": "R Madugalle", "team_1": "ENG ", "team_2": " WI", "format": "limited-over"}, "squad": {"team_1": {"0": {"name": "Brian Lara", "link": "/profiles/240/brian-lara"}, "1": {"name": "Corey Collymore", "link": "/profiles/245/corey-collymore"}, "2": {"name": "Chris Gayle", "link": "/profiles/247/chris-gayle"}, "3": {"name": "Wavell Hinds", "link": "/profiles/249/wavell-hinds"}, "4": {"name": "Jimmy Adams (c)", "link": "/profiles/4211/jimmy-adams"}, "5": {"name": "Sherwin Campbell", "link": "/profiles/4217/sherwin-campbell"}, "6": {"name": "Ridley Jacobs (wk)", "link": "/profiles/4223/ridley-jacobs"}, "7": {"name": "Nixon McLean", "link": "/profiles/4225/nixon-mclean"}, "8": {"name": "Franklyn Rose", "link": "/profiles/4229/franklyn-rose"}, "9": {"name": "Mervyn Dillon", "link": "/profiles/4233/mervyn-dillon"}, "10": {"name": "Ricardo Powell", "link": "/profiles/4241/ricardo-powell"}}, "team_2": {"0": {"name": "Brian Lara", "link": "/profiles/240/brian-lara"}, "1": {"name": "Corey Collymore", "link": "/profiles/245/corey-collymore"}, "2": {"name": "Chris Gayle", "link": "/profiles/247/chris-gayle"}, "3": {"name": "Wavell Hinds", "link": "/profiles/249/wavell-hinds"}, "4": {"name": "Jimmy Adams (c)", "link": "/profiles/4211/jimmy-adams"}, "5": {"name": "Sherwin Campbell", "link": "/profiles/4217/sherwin-campbell"}, "6": {"name": "Ridley Jacobs (wk)", "link": "/profiles/4223/ridley-jacobs"}, "7": {"name": "Nixon McLean", "link": "/profiles/4225/nixon-mclean"}, "8": {"name": "Franklyn Rose", "link": "/profiles/4229/franklyn-rose"}, "9": {"name": "Mervyn Dillon", "link": "/profiles/4233/mervyn-dillon"}, "10": {"name": "Ricardo Powell", "link": "/profiles/4241/ricardo-powell"}}}, "match_scores": {"innings_1": {"batting_data": {"0": {"name": "Marcus Trescothick", "result": "c & b Gayle", "runs": "49", "balls": "79", "4": "5", "6": "0", "SR": "62.03", "link": "/profiles/44/marcus-trescothick"}, "1": {"name": "Alec Stewart (c & wk)", "result": "c Gayle b McLean", "runs": "12", "balls": "20", "4": "2", "6": "0", "SR": "60.00", "link": "/profiles/5390/alec-stewart"}, "2": {"name": "Graeme Hick", "result": "c Jacobs b McLean", "runs": "12", "balls": "16", "4": "2", "6": "0", "SR": "75.00", "link": "/profiles/5395/graeme-hick"}, "3": {"name": "Matthew Maynard", "result": "b Collymore", "runs": "0", "balls": "5", "4": "0", "6": "0", "SR": "0.00", "link": "/profiles/5379/matthew-maynard"}, "4": {"name": "Graham Thorpe", "result": "c Dillon b Rose", "runs": "42", "balls": "76", "4": "2", "6": "0", "SR": "55.26", "link": "/profiles/5411/graham-thorpe"}, "5": {"name": "Craig White", "result": "c Jacobs b Rose", "runs": "10", "balls": "29", "4": "0", "6": "0", "SR": "34.48", "link": "/profiles/5414/craig-white"}, "6": {"name": "Mark Ealham", "result": "b Gayle", "runs": "17", "balls": "24", "4": "1", "6": "0", "SR": "70.83", "link": "/profiles/5426/mark-ealham"}, "7": {"name": "Robert Croft", "result": "not out", "runs": "5", "balls": "7", "4": "0", "6": "0", "SR": "71.43", "link": "/profiles/5428/robert-croft"}, "8": {"name": "Andy Caddick", "result": "c Gayle b Rose", "runs": "0", "balls": "6", "4": "0", "6": "0", "SR": "0.00", "link": "/profiles/5406/andy-caddick"}, "9": {"name": "Darren Gough", "result": "not out", "runs": "2", "balls": "4", "4": "0", "6": "0", "SR": "50.00", "link": "/profiles/63/darren-gough"}}, "bowling_data": {"0": {"name": "Nixon McLean", "overs": "8", "maiden": "2", "runs": "25", "wickets": "2", "no_balls": "0", "wides": "1", "economy": "3.13", "link": "/profiles/4225/nixon-mclean"}, "1": {"name": "Corey Collymore", "overs": "10", "maiden": "0", "runs": "46", "wickets": "1", "no_balls": "0", "wides": "2", "economy": "4.60", "link": "/profiles/245/corey-collymore"}, "2": {"name": "Franklyn Rose", "overs": "9", "maiden": "1", "runs": "42", "wickets": "3", "no_balls": "2", "wides": "0", "economy": "4.67", "link": "/profiles/4229/franklyn-rose"}, "3": {"name": "Chris Gayle", "overs": "10", "maiden": "1", "runs": "28", "wickets": "2", "no_balls": "0", "wides": "0", "economy": "2.80", "link": "/profiles/247/chris-gayle"}, "4": {"name": "Mervyn Dillon", "overs": "6.5", "maiden": "3", "runs": "13", "wickets": "0", "no_balls": "0", "wides": "0", "economy": "1.90", "link": "/profiles/4233/mervyn-dillon"}}}, "innings_2": {"batting_data": {}, "bowling_data": {}}}}